[
    {
        "name": "WorkerPool_1",
        "workers": [
            {
                "name": "Worker_1_1",
                "resources": [
                    {
                        "name": "CPU",
                        "quantity": 4
                    },
                    {
                        "name": "GPU",
                        "quantity": 2
                    }
                ]
            },

            {
                "name": "Worker_1_2",
                "resources": [
                    {
                        "name": "CPU",
                        "quantity": 4
                    }
                ]
            }
        ]
    },

    {
        "name": "WorkerPool_2",
        "workers": [
            {
                "name": "Worker_2_1",
                "resources": [
                    {
                        "name": "GPU",
                        "quantity": 1
                    }
                ]
            },

            {
                "name": "Worker_2_2",
                "resources": [
                    {
                        "name": "GPU",
                        "quantity": 1
                    },
                    {
                        "name": "CPU",
                        "quantity": 8
                    }
                ]
            }
        ]
    }
]
